README.md
setup.cfg
setup.py
npw.egg-info/PKG-INFO
npw.egg-info/SOURCES.txt
npw.egg-info/dependency_links.txt
npw.egg-info/entry_points.txt
npw.egg-info/requires.txt
npw.egg-info/top_level.txt
npwcli/__init__.py
npwcli/cli.py
npwcli/spider.py
npwcli/update_content.py
npwcli/utils.py