Metadata-Version: 1.1
Name: npw
Version: 1.1.3
Summary: A notepad.pw magician in your command line
Home-page: https://github.com/Chaitya62/notepadpw-cli
Author: Chaitya Shah
Author-email: chaitya.shah@somaiya.edu
License: UNKNOWN
Platform: UNKNOWN
Classifier: Development Status :: 4 - Beta
Classifier: Intended Audience :: Developers
Classifier: Natural Language :: English
Classifier: Programming Language :: Python
